dowsing/__init__.py
dowsing/_demo_pep517.py
dowsing/api.py
dowsing/flit.py
dowsing/maturin.py
dowsing/pep517.py
dowsing/poetry.py
dowsing/py.typed
dowsing/types.py
dowsing/setuptools/__init__.py
dowsing/setuptools/setup_and_metadata.py
dowsing/setuptools/setup_cfg_parsing.py
dowsing/setuptools/setup_py_parsing.py
dowsing/setuptools/types.py
dowsing/tests/__init__.py
dowsing/tests/__main__.py
dowsing/tests/api.py
dowsing/tests/flit.py
dowsing/tests/maturin.py
dowsing/tests/pep517.py
dowsing/tests/poetry.py
dowsing/tests/setuptools.py
dowsing/tests/setuptools_metadata.py
dowsing/tests/setuptools_types.py
dowsing-0.8.0.dist-info/LICENSE
dowsing-0.8.0.dist-info/METADATA
dowsing-0.8.0.dist-info/WHEEL
dowsing-0.8.0.dist-info/top_level.txt
dowsing-0.8.0.dist-info/RECORD
