Metadata-Version: 2.1
Name: dowsing
Version: 0.8.0
Summary: Guess metadata from sdist without running
Home-page: https://github.com/python-packaging/dowsing/
Author: Tim Hatch
Author-email: tim@timhatch.com
License: MIT
Platform: UNKNOWN
Requires-Python: >=3.6
Requires-Dist: highlighter (>=0.1.1)
Requires-Dist: imperfect (>=0.1.0)
Requires-Dist: LibCST (>=0.3.7)
Requires-Dist: tomlkit (>=0.2.0)
Requires-Dist: pkginfo (>=1.4.2)
